AUTHORS.rst
CONTRIBUTING.rst
HISTORY.rst
LICENSE
MANIFEST.in
README.rst
setup.cfg
setup.py
docs/Makefile
docs/authors.rst
docs/conf.py
docs/contributing.rst
docs/history.rst
docs/index.rst
docs/installation.rst
docs/make.bat
docs/readme.rst
docs/usage.rst
python_wrap_cases/__init__.py
python_wrap_cases/argumets_collection.py
python_wrap_cases/case_wrapper.py
python_wrap_cases/decorators.py
python_wrap_cases/metaclasses.py
python_wrap_cases/wrap_cases.py
python_wrap_cases.egg-info/PKG-INFO
python_wrap_cases.egg-info/SOURCES.txt
python_wrap_cases.egg-info/dependency_links.txt
python_wrap_cases.egg-info/not-zip-safe
python_wrap_cases.egg-info/pbr.json
python_wrap_cases.egg-info/requires.txt
python_wrap_cases.egg-info/top_level.txt
python_wrap_cases/generators/__init__.py
python_wrap_cases/generators/base_generator.py
python_wrap_cases/generators/custom_generator.py
python_wrap_cases/generators/func_generator.py
python_wrap_cases/generators/generatorst_factory.py
python_wrap_cases/generators/list_generator.py
python_wrap_cases/generators/range_generator.py
python_wrap_cases/generators/sync_list_generator.py
tests/__init__.py
tests/test_decorator.py
tests/cases/__init__.py
tests/cases/base_case.py
tests/cases/test_custom_generator.py
tests/cases/test_func_generator.py
tests/cases/test_list_generator.py
tests/cases/test_range_generator.py
tests/cases/test_simple_example.py
tests/cases/test_sync_list_generator.py
tests/cases/test_with_patch_multiple.py
tests/cases/test_with_patch_object.py
tests/cases/test_wrap_case_alias.py