Metadata-Version: 1.1
Name: python-wrap-cases
Version: 0.1.8
Summary: Simple library for generate test cases.
Home-page: https://github.com/erm0l0v/python_wrap_cases
Author: Kirill Ermolov
Author-email: erm0l0v@ya.ru
License: BSD
Keywords: python_wrap_cases,test cases,test,test with parameters,generate tests
Platform: UNKNOWN
Classifier: Development Status :: 5 - Production/Stable
Classifier: Intended Audience :: Developers
Classifier: License :: OSI Approved :: BSD License
Classifier: Natural Language :: English
Classifier: Programming Language :: Python :: 2
Classifier: Programming Language :: Python :: 2.6
Classifier: Programming Language :: Python :: 2.7
Classifier: Programming Language :: Python :: 3
Classifier: Programming Language :: Python :: 3.2
Classifier: Programming Language :: Python :: 3.3
Classifier: Programming Language :: Python :: 3.4
Classifier: Topic :: Software Development
Classifier: Topic :: Software Development :: Testing
